Metadata-Version: 2.4
Name: solo-server
Version: 0.5.0
Summary: Platform for Physiscal AI Inference.
Home-page: https://github.com/GetSoloTech/solo-server
Author: Dhruv Diddi
Author-email: dhruv.diddi@gmail.com
Requires-Python: >=3.8
License-File: LICENSE
Requires-Dist: typer
Requires-Dist: GPUtil
Requires-Dist: psutil
Requires-Dist: requests
Requires-Dist: rich
Requires-Dist: huggingface_hub
Requires-Dist: pydantic
Requires-Dist: lerobot[all]
Provides-Extra: dev
Requires-Dist: pytest; extra == "dev"
Requires-Dist: black; extra == "dev"
Requires-Dist: isort; extra == "dev"
Dynamic: author
Dynamic: author-email
Dynamic: description
Dynamic: description-content-type
Dynamic: home-page
Dynamic: license-file
Dynamic: provides-extra
Dynamic: requires-dist
Dynamic: requires-python
Dynamic: summary
